{"name":"build-javascript","namedChunkGroups":{"polyfill":{"name":"polyfill","assets":[{"name":"webpack-runtime-2815c3628059051cfe51.js","size":3192},{"name":"polyfill-50c015a41b6ab83c3743.js","size":85003}],"filteredAssets":0,"assetsSize":88195,"filteredAuxiliaryAssets":2,"auxiliaryAssetsSize":223969},"app":{"name":"app","assets":[{"name":"webpack-runtime-2815c3628059051cfe51.js","size":3192},{"name":"framework-2ca0d18e186e6327bbe0.js","size":140530},{"name":"app-4be5bb20a46cd9166a36.js","size":75172}],"filteredAssets":0,"assetsSize":218894,"filteredAuxiliaryAssets":3,"auxiliaryAssetsSize":644629},"component---src-pages-404-js":{"name":"component---src-pages-404-js","assets":[{"name":"component---src-pages-404-js-191d588695ce830f5cfb.js","size":774}],"filteredAssets":0,"assetsSize":774,"filteredAuxiliaryAssets":1,"auxiliaryAssetsSize":1747},"component---src-pages-index-js":{"name":"component---src-pages-index-js","assets":[{"name":"component---src-pages-index-js-f53bc5635b87061c7283.js","size":4433}],"filteredAssets":0,"assetsSize":4433,"filteredAuxiliaryAssets":1,"auxiliaryAssetsSize":7349}},"assetsByChunkName":{"polyfill":["webpack-runtime-2815c3628059051cfe51.js","polyfill-50c015a41b6ab83c3743.js"],"app":["webpack-runtime-2815c3628059051cfe51.js","framework-2ca0d18e186e6327bbe0.js","app-4be5bb20a46cd9166a36.js"],"component---src-pages-404-js":["component---src-pages-404-js-191d588695ce830f5cfb.js"],"component---src-pages-index-js":["component---src-pages-index-js-f53bc5635b87061c7283.js"]},"childAssetsByChunkName":{}}